storagekit
